LICENSE.txt
MANIFEST.in
README.md
requirements.txt
setup.py
examples/__init__.py
examples/ad_creation_utils.py
examples/async.py
examples/batch_create.py
examples/batch_pause.py
examples/batch_utils.py
examples/custom_audience_utils.py
examples/my_app_session.cfg.dist
examples/read_objects.py
examples/simple_create.py
examples/test.png
examples/upload_video.py
examples/dpa-update/dpa_search.py
examples/dpa-update/dpa_update.py
examples/dpa-update/stock_update.py
facebookads/__init__.py
facebookads/api.py
facebookads/apiconfig.py
facebookads/bootstrap.py
facebookads/exceptions.py
facebookads/exit_codes.py
facebookads/fb_ca_chain_bundle.crt
facebookads/mixins.py
facebookads/session.py
facebookads/specs.py
facebookads/typechecker.py
facebookads/video_uploader.py
facebookads.egg-info/PKG-INFO
facebookads.egg-info/SOURCES.txt
facebookads.egg-info/dependency_links.txt
facebookads.egg-info/requires.txt
facebookads.egg-info/top_level.txt
facebookads/adobjects/__init__.py
facebookads/adobjects/abstractcrudobject.py
facebookads/adobjects/abstractobject.py
facebookads/adobjects/ad.py
facebookads/adobjects/adaccount.py
facebookads/adobjects/adaccountdeliveryestimate.py
facebookads/adobjects/adaccountroas.py
facebookads/adobjects/adaccounttargetingunified.py
facebookads/adobjects/adaccountuser.py
facebookads/adobjects/adactivity.py
facebookads/adobjects/adasyncrequest.py
facebookads/adobjects/adasyncrequestset.py
facebookads/adobjects/adasyncrequestsetnotificationresult.py
facebookads/adobjects/adcampaigndeliveryestimate.py
facebookads/adobjects/adcreative.py
facebookads/adobjects/adcreativelinkdata.py
facebookads/adobjects/adcreativelinkdataapplinkspec.py
facebookads/adobjects/adcreativelinkdatacalltoaction.py
facebookads/adobjects/adcreativelinkdatacalltoactionvalue.py
facebookads/adobjects/adcreativelinkdatachildattachment.py
facebookads/adobjects/adcreativeobjectstoryspec.py
facebookads/adobjects/adcreativeofferdata.py
facebookads/adobjects/adcreativephotodata.py
facebookads/adobjects/adcreativeplacedata.py
facebookads/adobjects/adcreativetextdata.py
facebookads/adobjects/adcreativevideodata.py
