Metadata-Version: 1.1
Name: facebookads
Version: 2.10.1
Summary: Facebook Ads API SDK
Home-page: https://github.com/facebook/facebook-python-ads-sdk
Author: Facebook
Author-email: UNKNOWN
License: LICENSE.txt
Download-URL: https://github.com/facebook/facebook-python-ads-sdk/tarball/2.10.1
Platform: UNKNOWN
Classifier: Programming Language :: Python :: 2
Classifier: Programming Language :: Python :: 2.7
Classifier: Programming Language :: Python :: 3
Classifier: Programming Language :: Python :: 3.3
Classifier: Programming Language :: Python :: 3.4
